compenv/__init__.py
compenv/adapters/__init__.py
compenv/adapters/abstract.py
compenv/adapters/controller.py
compenv/adapters/distribution.py
compenv/adapters/entity.py
compenv/adapters/module.py
compenv/adapters/presenter.py
compenv/adapters/repository.py
compenv/adapters/translator.py
compenv/backend.py
compenv/infrastructure/__init__.py
compenv/infrastructure/entrypoint.py
compenv/infrastructure/facade.py
compenv/infrastructure/factory.py
compenv/infrastructure/hook.py
compenv/model/__init__.py
compenv/model/computation.py
compenv/model/environment.py
compenv/model/record.py
compenv/service/__init__.py
compenv/service/abstract.py
compenv/service/record.py
compenv-0.1.0.dist-info/WHEEL
compenv-0.1.0.dist-info/METADATA
compenv-0.1.0.dist-info/license_files/LICENSE
compenv-0.1.0.dist-info/RECORD
