Metadata-Version: 2.1
Name: compenv
Version: 0.1.0
Summary: Track information about the execution environment of computations
License: GPL-3.0-or-later
Author-email: Christoph Blessing <33834216+cblessing24@users.noreply.github.com>
Requires-Python: >=3.8
Requires-Dist: datajoint==0.12.9
Project-URL: homepage, https://github.com/sinzlab/compenv
